cnvcallertools/__init__.py
cnvcallertools/main.py
cnvcallertools/utilities/__init__.py
cnvcallertools/utilities/groupdescribe.py
cnvcallertools/utilities/parse.py
cnvcallertools-0.1.1.dist-info/DESCRIPTION.rst
cnvcallertools-0.1.1.dist-info/METADATA
cnvcallertools-0.1.1.dist-info/RECORD
cnvcallertools-0.1.1.dist-info/WHEEL
cnvcallertools-0.1.1.dist-info/entry_points.txt
cnvcallertools-0.1.1.dist-info/metadata.json
cnvcallertools-0.1.1.dist-info/top_level.txt
cnvcallertools-0.1.1.dist-info/zip-safe
