Metadata-Version: 2.0
Name: cnvcallertools
Version: 0.1.1
Summary: command line tool kits from analysis CNVcaller result
Home-page: https://github.com/silvewheat/CNVcaller_tools
Author: YudongCai
Author-email: yudongcai216@gmail.com
License: MIT
Keywords: python cnvcaller commandline
Platform: UNKNOWN
Requires-Dist: click
Requires-Dist: numpy
Requires-Dist: pandas
Requires-Dist: scipy
